pyosirix_example/__init__.py
pyosirix_example/__main__.py
pyosirix_example/client/__init__.py
pyosirix_example/client/client.py
pyosirix_example/server/__init__.py
pyosirix_example/server/data_loader.py
pyosirix_example/server/server.py
pyosirix_example/utilities/__init__.py
pyosirix_example/utilities/text_2_image.py
pyosirix_example/utilities/unit_conversions.py
pyosirix_example_project-0.0.1.dev24.dist-info/LICENSE
pyosirix_example_project-0.0.1.dev24.dist-info/METADATA
pyosirix_example_project-0.0.1.dev24.dist-info/WHEEL
pyosirix_example_project-0.0.1.dev24.dist-info/top_level.txt
pyosirix_example_project-0.0.1.dev24.dist-info/RECORD
