Metadata-Version: 2.1
Name: pyosirix_example_project
Version: 0.0.1.dev24
Summary: An example of a Python project that can be used to install into OsiriX
Author-email: Matthew D Blackledge <matthew.blackledge@icr.ac.uk>
Maintainer-email: Matthew D Blackledge <mattyblackledge@gmail.com>
Keywords: Dicom,Medical Imaging,Image Processing
Classifier: Programming Language :: Python :: 3
Classifier: Development Status :: 3 - Alpha
Classifier: License :: OSI Approved :: MIT License
Classifier: Natural Language :: English
Classifier: Operating System :: MacOS :: MacOS X
License-File: LICENSE
